{
  "name": "田原 果門",
  "nameEn": "Tahara Kamon",
  "age": 17,
  "title": "Portfolio",
  "developerTitle": "Web Developer & Mobile Developer",
  "about": {
    "image": "/images/about/TAHARA01.JPG",
    "furigana": "TaharaKamon",
    "description": "Web & Mobile アプリの開発を行っています。\n「やりたい」と思ったことは中途半端にせず、納得できるまで磨き上げて形にすることを大切にしています。\nユーザーが楽しさで夢中になれる体験をような届けるために、自分のスキルを最大限に引き出し開発に取り組んでいます！",
    "birthDate": "2008 05/04",
    "birthplace": "東京 江戸川区",
    "hobby": "甘いものを食べまくること。",
    "moreInfo": {
      "title": "",
      "description": "大切にしていること:\n・最後まで作り切ること\n・分かりやすく伝えること\n・楽しさと実用性の両立\n\n制作スタイル:\n・まず動くものを作る\n・触って違和感が出たら設計を見直す\n・見せ方まで含めて完成と考える",
      "items": []
    }
  },
  "contact": {
    "email": "taharacomeon.0504@gmail.com",
    "phone": "09054281623",
    "github": "https://github.com/Kamon-Tahara-504"
  },
  "experience": [
    {
      "id": "exp-1",
      "title": "プログラミングスクール受講",
      "company": "NcodeLabo",
      "period": "2022年5月",
      "description": "プログラミングを学び始める"
    },
    {
      "id": "exp-2",
      "title": "卒業",
      "company": "江戸川区東葛西中学校",
      "period": "2024年3月",
      "description": "中学校を卒業"
    },
    {
      "id": "exp-3",
      "title": "入学",
      "company": "KADOKAWAドワンゴ情報工科学院 高等部 東京校 IT総合科\n学校法人 角川ドワンゴ学園 S高等学校 普通科",
      "period": "2024年4月",
      "description": "エンジニアとして働きたいと思い入学を決める"
    },
    {
      "id": "exp-4",
      "title": "現在",
      "company": "WEBアプリケーションを 複数作成\n Mobileアプリケーションを 1つリリース",
      "period": "2025年12月",
      "description": "エンジニアリングを学びながら、Web & Mobileアプリの開発に取り組んでいます"
    }
  ],
  "skills": {
    "frontend": [
      { "name": "React", "level": 60, "startDate": "2025-04", "endDate": "2026-01" },
      { "name": "Next.js", "level": 60, "startDate": "2025-11", "endDate": null },
      { "name": "HTML", "level": 40 },
      { "name": "CSS", "level": 40 },
      { "name": "", "level": 0 }
    ], 
    "backend": [
      { "name": "C", "level": 80, "startDate": "2022-11", "endDate": "2024-03" },
      { "name": "Python", "level": 50, "startDate": "2023-11", "endDate": "2025-02" },
      { "name": "Django", "level": 50, "startDate": "2024-10", "endDate": "2025-02" },
      { "name": "Java", "level": 65, "startDate": "2025-04", "endDate": null },
      { "name": "TypeScript", "level": 60 }
    ],
    "mobile": [
      { "name": "Flutter", "level": 80, "startDate": "2025-03", "endDate": null },
      { "name": "Kotlin", "level": 15 },
      { "name": "Swift", "level": 15 },
      { "name": "React Native", "level": 35, "startDate": "2026-02", "endDate": null },
      { "name": "", "level": 0 }
    ],
    "tools": [
      { "name": "GitHub", "level": 65 },
      { "name": "Figma", "level": 40 },
      { "name": "VSCode", "level": 65 },
      { "name": "Eclipse", "level": 45 },
      { "name": "Xcode", "level": 30 }
    ]
  }
}

